collabutils/__init__.py
collabutils/base.py
collabutils/edictor.py
collabutils/googlesheets.py
collabutils/oc.py
collabutils/util.py
collabutils/zotero.py
collabutils-0.2.0.dist-info/LICENSE
collabutils-0.2.0.dist-info/METADATA
collabutils-0.2.0.dist-info/WHEEL
collabutils-0.2.0.dist-info/top_level.txt
collabutils-0.2.0.dist-info/RECORD
