Metadata-Version: 2.1
Name: collabutils
Version: 0.2.0
Summary: Utilities for collaborative data curation
Home-page: https://github.com/dlce-eva/collabutils
Author: Robert Forkel
Author-email: robert_forkel@eva.mpg.de
License: Apache 2.0
Project-URL: Bug Tracker, https://github.com/dlce-eva/collabutils/issues
Platform: any
Classifier: Development Status :: 4 - Beta
Classifier: Intended Audience :: Developers
Classifier: Intended Audience :: Science/Research
Classifier: Natural Language :: English
Classifier: Operating System :: OS Independent
Classifier: Programming Language :: Python :: 3
Classifier: Programming Language :: Python :: 3.7
Classifier: Programming Language :: Python :: 3.8
Classifier: Programming Language :: Python :: 3.9
Classifier: Programming Language :: Python :: 3.10
Classifier: Programming Language :: Python :: 3.11
Classifier: Programming Language :: Python :: Implementation :: CPython
Classifier: Programming Language :: Python :: Implementation :: PyPy
Classifier: License :: OSI Approved :: Apache Software License
Requires-Python: >=3.7
License-File: LICENSE
Requires-Dist: attrs (>=19.3)
Requires-Dist: clldutils (>=3.5)
Requires-Dist: csvw
Requires-Dist: pycldf
Provides-Extra: dev
Requires-Dist: build ; extra == 'dev'
Requires-Dist: tox ; extra == 'dev'
Requires-Dist: flake8 ; extra == 'dev'
Requires-Dist: wheel (>=0.36) ; extra == 'dev'
Requires-Dist: twine ; extra == 'dev'
Provides-Extra: docs
Requires-Dist: sphinx ; extra == 'docs'
Requires-Dist: sphinx-autodoc-typehints ; extra == 'docs'
Requires-Dist: sphinx-rtd-theme ; extra == 'docs'
Provides-Extra: googlesheets
Requires-Dist: gspread (==3.7) ; extra == 'googlesheets'
Provides-Extra: owncloud
Requires-Dist: pyocclient ; extra == 'owncloud'
Requires-Dist: openpyxl ; extra == 'owncloud'
Provides-Extra: test
Requires-Dist: pytest (>=4.3) ; extra == 'test'
Requires-Dist: pytest-mock ; extra == 'test'
Requires-Dist: pytest-cov ; extra == 'test'
Requires-Dist: coverage (>=4.2) ; extra == 'test'
Requires-Dist: gspread (==3.7) ; extra == 'test'
Requires-Dist: pyocclient ; extra == 'test'
Requires-Dist: openpyxl ; extra == 'test'
Requires-Dist: pybtex ; extra == 'test'
Requires-Dist: pyzotero ; extra == 'test'
Provides-Extra: zotero
Requires-Dist: pyzotero ; extra == 'zotero'
Requires-Dist: pybtex ; extra == 'zotero'
